chatintents/ChatIntents.py
chatintents/__init__.py
chatintents-0.0.1.dist-info/LICENSE
chatintents-0.0.1.dist-info/METADATA
chatintents-0.0.1.dist-info/WHEEL
chatintents-0.0.1.dist-info/top_level.txt
chatintents-0.0.1.dist-info/RECORD
